{
    "Coleccionables": [
        {
            "id": 0,
            "description": "",
            "yasalio": true
        },
        {
            "id": 1,
            "description": "",
            "yasalio": true
        },
        {
            "id": 2,
            "description": "",
            "yasalio": true
        },
        {
            "id": 3,
            "description": "",
            "yasalio": true
        },
        {
            "id": 4,
            "description": "",
            "yasalio": false
        },
        {
            "id": 5,
            "description": "",
            "yasalio": false
        },
        {
            "id": 6,
            "description": "",
            "yasalio": false
        },
        {
            "id": 7,
            "description": "",
            "yasalio": false
        },
        {
            "id": 8,
            "description": "",
            "yasalio": false
        },
        {
            "id": 9,
            "description": "",
            "yasalio": false
        },
        {
            "id": 10,
            "description": "",
            "yasalio": false
        },
        {
            "id": 11,
            "description": "",
            "yasalio": false
        },
        {
            "id": 12,
            "description": "",
            "yasalio": false
        },
        {
            "id": 13,
            "description": "",
            "yasalio": false
        },
        {
            "id": 14,
            "description": "",
            "yasalio": false
        },
        {
            "id": 15,
            "description": "",
            "yasalio": false
        },
        {
            "id": 16,
            "description": "",
            "yasalio": false
        },
        {
            "id": 17,
            "description": "",
            "yasalio": false
        },
        {
            "id": 18,
            "description": "",
            "yasalio": false
        },
        {
            "id": 19,
            "description": "",
            "yasalio": false
        },
        {
            "id": 20,
            "description": "",
            "yasalio": false
        },
        {
            "id": 21,
            "description": "",
            "yasalio": false
        },
        {
            "id": 22,
            "description": "",
            "yasalio": false
        },
        {
            "id": 23,
            "description": "",
            "yasalio": false
        },
        {
            "id": 24,
            "description": "",
            "yasalio": false
        },
        {
            "id": 25,
            "description": "",
            "yasalio": false
        },
        {
            "id": 26,
            "description": "",
            "yasalio": false
        },
        {
            "id": 27,
            "description": "",
            "yasalio": false
        },
        {
            "id": 28,
            "description": "",
            "yasalio": false
        },
        {
            "id": 29,
            "description": "",
            "yasalio": false
        },
        {
            "id": 30,
            "description": "",
            "yasalio": false
        },
        {
            "id": 31,
            "description": "",
            "yasalio": false
        },
        {
            "id": 32,
            "description": "",
            "yasalio": false
        },
        {
            "id": 33,
            "description": "",
            "yasalio": false
        },
        {
            "id": 34,
            "description": "",
            "yasalio": false
        },
        {
            "id": 35,
            "description": "",
            "yasalio": false
        },
        {
            "id": 36,
            "description": "",
            "yasalio": false
        },
        {
            "id": 37,
            "description": "",
            "yasalio": false
        },
        {
            "id": 38,
            "description": "",
            "yasalio": false
        },
        {
            "id": 39,
            "description": "",
            "yasalio": false
        },
        {
            "id": 40,
            "description": "",
            "yasalio": false
        },
        {
            "id": 41,
            "description": "",
            "yasalio": false
        },
        {
            "id": 42,
            "description": "",
            "yasalio": false
        },
        {
            "id": 43,
            "description": "",
            "yasalio": false
        },
        {
            "id": 44,
            "description": "",
            "yasalio": false
        },
        {
            "id": 45,
            "description": "",
            "yasalio": false
        },
        {
            "id": 46,
            "description": "",
            "yasalio": false
        },
        {
            "id": 47,
            "description": "",
            "yasalio": false
        },
        {
            "id": 48,
            "description": "",
            "yasalio": false
        },
        {
            "id": 49,
            "description": "",
            "yasalio": false
        },
        {
            "id": 50,
            "description": "",
            "yasalio": false
        },
        {
            "id": 51,
            "description": "",
            "yasalio": false
        },
        {
            "id": 52,
            "description": "",
            "yasalio": false
        },
        {
            "id": 53,
            "description": "",
            "yasalio": false
        },
        {
            "id": 54,
            "description": "",
            "yasalio": false
        },
        {
            "id": 55,
            "description": "",
            "yasalio": false
        },
        {
            "id": 56,
            "description": "",
            "yasalio": false
        },
        {
            "id": 57,
            "description": "",
            "yasalio": false
        },
        {
            "id": 58,
            "description": "",
            "yasalio": false
        },
        {
            "id": 59,
            "description": "",
            "yasalio": false
        },
        {
            "id": 60,
            "description": "",
            "yasalio": false
        },
        {
            "id": 61,
            "description": "",
            "yasalio": false
        },
        {
            "id": 62,
            "description": "",
            "yasalio": false
        },
        {
            "id": 63,
            "description": "",
            "yasalio": false
        },
        {
            "id": 64,
            "description": "",
            "yasalio": false
        },
        {
            "id": 65,
            "description": "",
            "yasalio": false
        },
        {
            "id": 66,
            "description": "",
            "yasalio": false
        },
        {
            "id": 67,
            "description": "",
            "yasalio": false
        },
        {
            "id": 68,
            "description": "",
            "yasalio": false
        },
        {
            "id": 69,
            "description": "",
            "yasalio": false
        },
        {
            "id": 70,
            "description": "",
            "yasalio": false
        },
        {
            "id": 71,
            "description": "",
            "yasalio": false
        },
        {
            "id": 72,
            "description": "",
            "yasalio": false
        },
        {
            "id": 73,
            "description": "",
            "yasalio": false
        },
        {
            "id": 74,
            "description": "",
            "yasalio": false
        },
        {
            "id": 75,
            "description": "",
            "yasalio": false
        },
        {
            "id": 76,
            "description": "",
            "yasalio": false
        },
        {
            "id": 77,
            "description": "",
            "yasalio": false
        },
        {
            "id": 78,
            "description": "",
            "yasalio": false
        },
        {
            "id": 79,
            "description": "",
            "yasalio": false
        },
        {
            "id": 80,
            "description": "",
            "yasalio": false
        },
        {
            "id": 81,
            "description": "",
            "yasalio": false
        },
        {
            "id": 82,
            "description": "",
            "yasalio": false
        },
        {
            "id": 83,
            "description": "",
            "yasalio": false
        },
        {
            "id": 84,
            "description": "",
            "yasalio": false
        },
        {
            "id": 85,
            "description": "",
            "yasalio": false
        },
        {
            "id": 86,
            "description": "",
            "yasalio": false
        },
        {
            "id": 87,
            "description": "",
            "yasalio": false
        },
        {
            "id": 88,
            "description": "",
            "yasalio": false
        },
        {
            "id": 89,
            "description": "",
            "yasalio": false
        },
        {
            "id": 90,
            "description": "",
            "yasalio": false
        },
        {
            "id": 91,
            "description": "",
            "yasalio": false
        },
        {
            "id": 92,
            "description": "",
            "yasalio": false
        },
        {
            "id": 93,
            "description": "",
            "yasalio": false
        },
        {
            "id": 94,
            "description": "",
            "yasalio": false
        },
        {
            "id": 95,
            "description": "",
            "yasalio": false
        },
        {
            "id": 96,
            "description": "",
            "yasalio": false
        },
        {
            "id": 97,
            "description": "",
            "yasalio": false
        },
        {
            "id": 98,
            "description": "",
            "yasalio": false
        },
        {
            "id": 99,
            "description": "",
            "yasalio": false
        },
        {
            "id": 100,
            "description": "",
            "yasalio": false
        },
        {
            "id": 101,
            "description": "",
            "yasalio": false
        },
        {
            "id": 102,
            "description": "",
            "yasalio": false
        },
        {
            "id": 103,
            "description": "",
            "yasalio": false
        },
        {
            "id": 104,
            "description": "",
            "yasalio": false
        },
        {
            "id": 105,
            "description": "",
            "yasalio": false
        },
        {
            "id": 106,
            "description": "",
            "yasalio": false
        },
        {
            "id": 107,
            "description": "",
            "yasalio": false
        },
        {
            "id": 108,
            "description": "",
            "yasalio": false
        },
        {
            "id": 109,
            "description": "",
            "yasalio": false
        },
        {
            "id": 110,
            "description": "",
            "yasalio": false
        },
        {
            "id": 111,
            "description": "",
            "yasalio": false
        },
        {
            "id": 112,
            "description": "",
            "yasalio": false
        },
        {
            "id": 113,
            "description": "",
            "yasalio": false
        },
        {
            "id": 114,
            "description": "",
            "yasalio": false
        },
        {
            "id": 115,
            "description": "",
            "yasalio": false
        },
        {
            "id": 116,
            "description": "",
            "yasalio": false
        },
        {
            "id": 117,
            "description": "",
            "yasalio": false
        },
        {
            "id": 118,
            "description": "",
            "yasalio": false
        },
        {
            "id": 119,
            "description": "",
            "yasalio": false
        },
        {
            "id": 120,
            "description": "",
            "yasalio": false
        },
        {
            "id": 121,
            "description": "",
            "yasalio": false
        },
        {
            "id": 122,
            "description": "",
            "yasalio": false
        },
        {
            "id": 123,
            "description": "",
            "yasalio": false
        },
        {
            "id": 124,
            "description": "",
            "yasalio": false
        },
        {
            "id": 125,
            "description": "",
            "yasalio": false
        },
        {
            "id": 126,
            "description": "",
            "yasalio": false
        },
        {
            "id": 127,
            "description": "",
            "yasalio": false
        },
        {
            "id": 128,
            "description": "",
            "yasalio": false
        },
        {
            "id": 129,
            "description": "",
            "yasalio": false
        },
        {
            "id": 130,
            "description": "",
            "yasalio": false
        },
        {
            "id": 131,
            "description": "",
            "yasalio": false
        },
        {
            "id": 132,
            "description": "",
            "yasalio": false
        },
        {
            "id": 133,
            "description": "",
            "yasalio": false
        },
        {
            "id": 134,
            "description": "",
            "yasalio": false
        },
        {
            "id": 135,
            "description": "",
            "yasalio": false
        },
        {
            "id": 136,
            "description": "",
            "yasalio": false
        },
        {
            "id": 137,
            "description": "",
            "yasalio": false
        },
        {
            "id": 138,
            "description": "",
            "yasalio": false
        },
        {
            "id": 139,
            "description": "",
            "yasalio": false
        },
        {
            "id": 140,
            "description": "",
            "yasalio": false
        },
        {
            "id": 141,
            "description": "",
            "yasalio": false
        },
        {
            "id": 142,
            "description": "",
            "yasalio": false
        },
        {
            "id": 143,
            "description": "",
            "yasalio": false
        },
        {
            "id": 144,
            "description": "",
            "yasalio": false
        },
        {
            "id": 145,
            "description": "",
            "yasalio": false
        },
        {
            "id": 146,
            "description": "",
            "yasalio": false
        },
        {
            "id": 147,
            "description": "",
            "yasalio": false
        },
        {
            "id": 148,
            "description": "",
            "yasalio": false
        },
        {
            "id": 149,
            "description": "",
            "yasalio": false
        },
        {
            "id": 150,
            "description": "",
            "yasalio": false
        },
        {
            "id": 151,
            "description": "",
            "yasalio": false
        },
        {
            "id": 152,
            "description": "",
            "yasalio": false
        },
        {
            "id": 153,
            "description": "",
            "yasalio": false
        },
        {
            "id": 154,
            "description": "",
            "yasalio": false
        },
        {
            "id": 155,
            "description": "",
            "yasalio": false
        },
        {
            "id": 156,
            "description": "",
            "yasalio": false
        },
        {
            "id": 157,
            "description": "",
            "yasalio": false
        },
        {
            "id": 158,
            "description": "",
            "yasalio": false
        },
        {
            "id": 159,
            "description": "",
            "yasalio": false
        },
        {
            "id": 160,
            "description": "",
            "yasalio": false
        },
        {
            "id": 161,
            "description": "",
            "yasalio": false
        },
        {
            "id": 162,
            "description": "",
            "yasalio": false
        },
        {
            "id": 163,
            "description": "",
            "yasalio": false
        },
        {
            "id": 164,
            "description": "",
            "yasalio": false
        },
        {
            "id": 165,
            "description": "",
            "yasalio": false
        },
        {
            "id": 166,
            "description": "",
            "yasalio": false
        },
        {
            "id": 167,
            "description": "",
            "yasalio": false
        },
        {
            "id": 168,
            "description": "",
            "yasalio": false
        },
        {
            "id": 169,
            "description": "",
            "yasalio": false
        },
        {
            "id": 170,
            "description": "",
            "yasalio": false
        },
        {
            "id": 171,
            "description": "",
            "yasalio": false
        },
        {
            "id": 172,
            "description": "",
            "yasalio": false
        },
        {
            "id": 173,
            "description": "",
            "yasalio": false
        },
        {
            "id": 174,
            "description": "",
            "yasalio": false
        },
        {
            "id": 175,
            "description": "",
            "yasalio": false
        },
        {
            "id": 176,
            "description": "",
            "yasalio": false
        },
        {
            "id": 177,
            "description": "",
            "yasalio": false
        },
        {
            "id": 178,
            "description": "",
            "yasalio": false
        },
        {
            "id": 179,
            "description": "",
            "yasalio": false
        },
        {
            "id": 180,
            "description": "",
            "yasalio": false
        }
    ]
}